[
  {
    "name": "g16_a0.75_fb0.050",
    "group_size": 16,
    "alpha": 0.75,
    "fallback_ratio": 0.05,
    "mean_cosine": 0.9961978793144226,
    "min_cosine": 0.9948387145996094,
    "mean_relative_error": 0.08162963390350342,
    "gate_mse": 0.008720332756638527,
    "up_mse": 0.008720332756638527,
    "down_mse": 0.008717916905879974,
    "fallback_cols_gate": 358,
    "fallback_cols_up": 358,
    "fallback_cols_down": 154,
    "pass_995": true
  },
  {
    "name": "g16_a1.25_fb0.050",
    "group_size": 16,
    "alpha": 1.25,
    "fallback_ratio": 0.05,
    "mean_cosine": 0.9960669279098511,
    "min_cosine": 0.995423436164856,
    "mean_relative_error": 0.08547961711883545,
    "gate_mse": 0.008839292451739311,
    "up_mse": 0.008839292451739311,
    "down_mse": 0.00883798860013485,
    "fallback_cols_gate": 358,
    "fallback_cols_up": 358,
    "fallback_cols_down": 154,
    "pass_995": true
  },
  {
    "name": "g16_a0.75_fb0.020",
    "group_size": 16,
    "alpha": 0.75,
    "fallback_ratio": 0.02,
    "mean_cosine": 0.9957898855209351,
    "min_cosine": 0.9946860671043396,
    "mean_relative_error": 0.0888005942106247,
    "gate_mse": 0.008720332756638527,
    "up_mse": 0.008720332756638527,
    "down_mse": 0.008717916905879974,
    "fallback_cols_gate": 143,
    "fallback_cols_up": 143,
    "fallback_cols_down": 61,
    "pass_995": true
  },
  {
    "name": "g16_a1.00_fb0.020",
    "group_size": 16,
    "alpha": 1.0,
    "fallback_ratio": 0.02,
    "mean_cosine": 0.9955441355705261,
    "min_cosine": 0.9953334927558899,
    "mean_relative_error": 0.09447593986988068,
    "gate_mse": 0.008865287527441978,
    "up_mse": 0.008865287527441978,
    "down_mse": 0.008865635842084885,
    "fallback_cols_gate": 143,
    "fallback_cols_up": 143,
    "fallback_cols_down": 61,
    "pass_995": true
  },
  {
    "name": "g16_a1.00_fb0.000",
    "group_size": 16,
    "alpha": 1.0,
    "fallback_ratio": 0.0,
    "mean_cosine": 0.9955426454544067,
    "min_cosine": 0.9953351616859436,
    "mean_relative_error": 0.0945134311914444,
    "gate_mse": 0.008865287527441978,
    "up_mse": 0.008865287527441978,
    "down_mse": 0.008865635842084885,
    "fallback_cols_gate": 0,
    "fallback_cols_up": 0,
    "fallback_cols_down": 0,
    "pass_995": true
  },
  {
    "name": "g32_a1.25_fb0.050",
    "group_size": 32,
    "alpha": 1.25,
    "fallback_ratio": 0.05,
    "mean_cosine": 0.9954096674919128,
    "min_cosine": 0.9946737289428711,
    "mean_relative_error": 0.09258715808391571,
    "gate_mse": 0.010224621742963791,
    "up_mse": 0.010224621742963791,
    "down_mse": 0.010225286707282066,
    "fallback_cols_gate": 358,
    "fallback_cols_up": 358,
    "fallback_cols_down": 154,
    "pass_995": true
  },
  {
    "name": "g16_a0.75_fb0.000",
    "group_size": 16,
    "alpha": 0.75,
    "fallback_ratio": 0.0,
    "mean_cosine": 0.9953721761703491,
    "min_cosine": 0.9945225715637207,
    "mean_relative_error": 0.09589247405529022,
    "gate_mse": 0.008720332756638527,
    "up_mse": 0.008720332756638527,
    "down_mse": 0.008717916905879974,
    "fallback_cols_gate": 0,
    "fallback_cols_up": 0,
    "fallback_cols_down": 0,
    "pass_995": true
  },
  {
    "name": "g64_a1.25_fb0.050",
    "group_size": 64,
    "alpha": 1.25,
    "fallback_ratio": 0.05,
    "mean_cosine": 0.9949530363082886,
    "min_cosine": 0.994203507900238,
    "mean_relative_error": 0.09761914610862732,
    "gate_mse": 0.011204782873392105,
    "up_mse": 0.011204782873392105,
    "down_mse": 0.011204361915588379,
    "fallback_cols_gate": 358,
    "fallback_cols_up": 358,
    "fallback_cols_down": 154,
    "pass_995": false
  },
  {
    "name": "g128_a1.00_fb0.000",
    "group_size": 128,
    "alpha": 1.0,
    "fallback_ratio": 0.0,
    "mean_cosine": 0.9940214157104492,
    "min_cosine": 0.9936996698379517,
    "mean_relative_error": 0.11014146357774734,
    "gate_mse": 0.011853585951030254,
    "up_mse": 0.011853585951030254,
    "down_mse": 0.01185540109872818,
    "fallback_cols_gate": 0,
    "fallback_cols_up": 0,
    "fallback_cols_down": 0,
    "pass_995": false
  }
]